[
	{
		"name": "Knock on the Coffin Lid",
		"price": "$34.99",
		"image": "https://store-images.s-microsoft.com/image/apps.10626.13978778908125358.75c586be-ef14-4436-9b7e-abbbf62dc94c.7b94e506-4fe5-4c11-ac3b-adefde70ea38?q=90&w=177&h=177",
		"uuid": "9N4PVQQ541CC",
		"platforms": [
			"Knock on the Coffin Lid"
		]
	},
	{
		"name": "Kittens and Yarn",
		"price": "$2.99",
		"image": "https://store-images.s-microsoft.com/image/apps.10681.14522022404840744.afd75448-a179-43b4-beda-ca716e2cc98b.fbdf8c06-425b-4d05-8ca0-7fd85e46fcaf?q=90&w=177&h=177",
		"uuid": "9P0ZD22M5K6H",
		"platforms": [
			"Kittens and Yarn"
		]
	},
	{
		"name": "Knight's Night!",
		"price": "$4.99",
		"image": "https://store-images.s-microsoft.com/image/apps.30276.13983002153330885.f60d9396-973f-4f3f-a6fd-379bd51ffc18.26ed5e65-5ffd-4bfc-86b0-46d16dd66a84?q=90&w=177&h=177",
		"uuid": "9N4HH82TQ2ZN",
		"platforms": [
			"Knight's Night!"
		]
	},
	{
		"name": "Kvark",
		"price": "$19.49",
		"image": "https://store-images.s-microsoft.com/image/apps.3023.13983133331568893.7c135a31-37eb-4903-bf8b-6fb070f06d27.60771986-a308-4924-9fd0-27001ae3b412?q=90&w=177&h=177",
		"uuid": "9N4GVP3WFLG6",
		"platforms": [
			"Kvark"
		]
	},
	{
		"name": "Kaiju Big Battel: Fighto Fantasy",
		"price": "$19.99",
		"image": "https://store-images.s-microsoft.com/image/apps.5469.14276827058460105.f36f9294-ac13-494a-8521-161906dfa251.4a4f2fcb-45f6-436a-9855-5ef1e6b281b7?q=90&w=177&h=177",
		"uuid": "9PJRN1TTX0HX",
		"platforms": [
			"Kaiju Big Battel: Fighto Fantasy"
		]
	},
	{
		"name": "Kingdom Come: Deliverance II",
		"price": "$69.99+",
		"image": "https://store-images.s-microsoft.com/image/apps.63936.13979588110779567.5e6f9542-73ca-4800-a714-e6819fafc7f7.76f929f7-c7fe-476b-ad30-a807168ecc09?q=90&w=177&h=177",
		"uuid": "9N4W31HSMVVD",
		"platforms": [
			"Kingdom Come: Deliverance II"
		]
	},
	{
		"name": "Kingdom Come: Deliverance II Gold Edition",
		"price": "$89.99+",
		"image": "https://store-images.s-microsoft.com/image/apps.15724.13789854240997602.73d7fbd1-c95c-4abc-acbc-b1cb92ab1363.1c3ba30e-8747-40f5-bb13-b0373f23bd55?q=90&w=177&h=177",
		"uuid": "9PBHX1S4DGZ4",
		"platforms": [
			"Kingdom Come: Deliverance II Gold Edition"
		]
	},
	{
		"name": "Kingdom Come: Deliverance - Royal Edition",
		"price": "$39.99+",
		"image": "https://store-images.s-microsoft.com/image/apps.25735.69163470958040887.ac07b798-77c0-4384-b8ae-89bb2b54db97.073fc5d8-a70b-4f87-b90a-45de4422821d?q=90&w=177&h=177",
		"uuid": "BQJKD0DJ1Q8J",
		"platforms": [
			"Kingdom Come: Deliverance - Royal Edition"
		]
	},
	{
		"name": "KINGDOM HEARTS - HD 1.5+2.5 ReMIX -",
		"price": "$49.99",
		"image": "https://store-images.s-microsoft.com/image/apps.38120.13632199716185998.13299b88-5419-46be-b574-e039f0e17d14.b0f874e0-8a21-4b7b-8212-4c49284d3346?q=90&w=177&h=177",
		"uuid": "9NHDF1Q6HGMH",
		"platforms": [
			"KINGDOM HEARTS - HD 1.5+2.5 ReMIX -"
		]
	},
	{
		"name": "KINGDOM HEARTS Ⅲ",
		"price": "$59.99+",
		"image": "https://store-images.s-microsoft.com/image/apps.47592.64731639180234187.ef9f08c7-a053-4657-a057-02cbb6029516.c22b8c7a-cf1e-4d66-a4c6-f62ade1cb51d?q=90&w=177&h=177",
		"uuid": "C08MW8XHQN9G",
		"platforms": [
			"KINGDOM HEARTS Ⅲ"
		]
	},
	{
		"name": "Kingdom Come: Deliverance",
		"price": "$29.99+",
		"image": "https://store-images.s-microsoft.com/image/apps.8869.14531461635142175.a52f54b0-3b79-489a-a2c3-d2c875b56013.2be017c4-ff69-4370-ac21-2471d12d1d3f?q=90&w=177&h=177",
		"uuid": "9P3T7HVKM6D0",
		"platforms": [
			"Kingdom Come: Deliverance"
		]
	},
	{
		"name": "Killing Floor 2",
		"price": "$29.99+",
		"image": "https://store-images.s-microsoft.com/image/apps.14907.70222240565100850.b7bb7fed-111f-4c72-b8c3-85a647cdf303.1a203762-50c5-4b1f-b2b7-112bcbca8060?q=90&w=177&h=177",
		"uuid": "BSB132ZQVWZM",
		"platforms": [
			"Killing Floor 2"
		]
	},
	{
		"name": "Kong: Survivor Instinct",
		"price": "$24.99",
		"image": "https://store-images.s-microsoft.com/image/apps.24246.13875559656716690.257dd98d-c782-4e98-81ef-02b78293ff04.f8952f4b-6502-4e19-84a4-1ced5f70b3cc?q=90&w=177&h=177",
		"uuid": "9MZG9HFBWDSF",
		"platforms": [
			"Kong: Survivor Instinct"
		]
	},
	{
		"name": "KINGDOM HEARTS HD 2.8 Final Chapter Prologue",
		"price": "$59.99",
		"image": "https://store-images.s-microsoft.com/image/apps.32959.13522090809526555.7ecdae69-8b63-406b-b33c-d10c74d550da.5df66911-4c12-4a06-b34c-389bf5da53eb?q=90&w=177&h=177",
		"uuid": "9NB80T1XC43B",
		"platforms": [
			"KINGDOM HEARTS HD 2.8 Final Chapter Prologue"
		]
	},
	{
		"name": "KIBORG",
		"price": "$29.99",
		"image": "https://store-images.s-microsoft.com/image/apps.2468.14019020280751797.1438e0e9-0c29-4439-b358-dbdb6ab45d79.91568fe5-d8a3-4dce-a1dd-4eea7089132e?q=90&w=177&h=177",
		"uuid": "9N6GLJSQBNZD",
		"platforms": [
			"KIBORG"
		]
	},
	{
		"name": "Killer Instinct",
		"price": "Free+",
		"image": "https://store-images.s-microsoft.com/image/apps.27218.13510798886190122.27ebfbc6-d999-40a1-ac11-cba87a75b91a.40c1ced9-b836-4d34-9684-a9ac994d32f0?q=90&w=177&h=177",
		"uuid": "9NBLGGH1Z149",
		"platforms": [
			"Killer Instinct"
		]
	},
	{
		"name": "Killer Klowns From Outer Space: The Game",
		"price": "$39.99+",
		"image": "https://store-images.s-microsoft.com/image/apps.65430.14398907729629362.cdb4e5b7-2ca0-4338-9e6f-1baf9c50098d.90ba5183-4a83-4753-bfff-1704338dbb4c?q=90&w=177&h=177",
		"uuid": "9NVHCV80ZZMH",
		"platforms": [
			"Killer Klowns From Outer Space: The Game"
		]
	},
	{
		"name": "Kanjozoku Game - レーサーCar Racing & Highway Driving Simulator Games",
		"price": "$14.99",
		"image": "https://store-images.s-microsoft.com/image/apps.7909.14433706522442007.9b65340a-6ab0-47f8-a8a3-a400540adde1.8f315ed8-bb61-4227-a69b-10f9a8ea571c?q=90&w=177&h=177",
		"uuid": "9NX9H4RKS43Q",
		"platforms": [
			"Kanjozoku Game - レーサーCar Racing & Highway Driving Simulator Games"
		]
	},
	{
		"name": "Kingdoms and Castles",
		"price": "$14.99",
		"image": "https://store-images.s-microsoft.com/image/apps.59096.14513796531784321.fb1e411b-701d-4129-9300-e7b7f072a372.399945f2-2bbd-43ed-adf1-6d2978415b4d?q=90&w=177&h=177",
		"uuid": "9P15B79HJ6GV",
		"platforms": [
			"Kingdoms and Castles"
		]
	},
	{
		"name": "Killing Floor 3",
		"price": "$39.99+",
		"image": "https://store-images.s-microsoft.com/image/apps.30312.13520303150219552.8acfc9d2-8573-4513-95da-c1751e9b1bf3.4c324679-f297-4e09-b696-622ccdd8335b?q=90&w=177&h=177",
		"uuid": "9NB4G2RLNZW9",
		"platforms": [
			"Killing Floor 3"
		]
	},
	{
		"name": "Kingdom Two Crowns",
		"price": "$19.99",
		"image": "https://store-images.s-microsoft.com/image/apps.55801.71673052342730938.755a1636-e311-4e76-b788-08cd89fc0781.3fd7fbba-15a2-4102-94bf-4d8c3e6baeae?q=90&w=177&h=177",
		"uuid": "BWT2GPVWCH2F",
		"platforms": [
			"Kingdom Two Crowns"
		]
	},
	{
		"name": "KINGDOM HEARTS Melody of Memory (International)",
		"price": "$59.99",
		"image": "https://store-images.s-microsoft.com/image/apps.45711.13996632189236414.6b579efe-3833-4c8e-846c-120bf230abc5.bc9b9981-31d7-4238-8f97-17416868f3ae?q=90&w=177&h=177",
		"uuid": "9N3SDL8MWH6K",
		"platforms": [
			"KINGDOM HEARTS Melody of Memory (International)"
		]
	},
	{
		"name": "King Arthur: Knight's Tale",
		"price": "$44.99+",
		"image": "https://store-images.s-microsoft.com/image/apps.11215.13707162186941946.30ceb381-1d5c-444a-ae31-7c960f510fd3.9e6a092a-f1f5-46b7-b84c-d1cad8702e90?q=90&w=177&h=177",
		"uuid": "9NLQ6HBNZC53",
		"platforms": [
			"King Arthur: Knight's Tale"
		]
	},
	{
		"name": "Kingdoms of Amalur: Re-Reckoning FATE Edition",
		"price": "$54.99+",
		"image": "https://store-images.s-microsoft.com/image/apps.1558.13920429802778076.c7644182-8bb7-44aa-8b42-c9b423d72ea8.76d7b40a-56db-4584-9113-fe6bf79be4c2?q=90&w=177&h=177",
		"uuid": "9N0J1QQZQV83",
		"platforms": [
			"Kingdoms of Amalur: Re-Reckoning FATE Edition"
		]
	},
	{
		"name": "Kena: Bridge of Spirits",
		"price": "$39.99",
		"image": "https://store-images.s-microsoft.com/image/apps.10564.13615498624789457.0f1e2b4a-813c-4d19-97bd-5970188ac852.cc7c2882-82a0-4cb4-88d1-7e1e191615e3?q=90&w=177&h=177",
		"uuid": "9NDNM3HX77R0",
		"platforms": [
			"Kena: Bridge of Spirits"
		]
	},
	{
		"name": "Kill It With Fire: Exterminator Edition",
		"price": "$19.99+",
		"image": "https://store-images.s-microsoft.com/image/apps.24037.14567336960453181.9d1f44fa-3220-4cb7-8371-331c35c106bb.2e8f40a6-689c-483b-83d2-ae20a3286289?q=90&w=177&h=177",
		"uuid": "9P5L7BGTTW7N",
		"platforms": [
			"Kill It With Fire: Exterminator Edition"
		]
	},
	{
		"name": "KILL KNIGHT",
		"price": "$14.99",
		"image": "https://store-images.s-microsoft.com/image/apps.44791.13759861295417217.01a4fec1-57b7-4188-9013-81a2eb92960b.4118b18a-64bf-4155-8fa4-88981988613c?q=90&w=177&h=177",
		"uuid": "9NR6CZSLBV7X",
		"platforms": [
			"KILL KNIGHT"
		]
	},
	{
		"name": "KartRider: Drift",
		"price": "Free",
		"image": "https://store-images.s-microsoft.com/image/apps.23662.69575354529436354.9dfb6646-2549-4cc9-9227-38b166655993.5a17d4a6-5ea0-4ba2-b8e3-0d5bc374b997?q=90&w=177&h=177",
		"uuid": "BR8K0RVDQJS5",
		"platforms": [
			"KartRider: Drift"
		]
	},
	{
		"name": "Killing Time: Resurrected",
		"price": "$24.99",
		"image": "https://store-images.s-microsoft.com/image/apps.2165.14116023529329703.cdf0c92b-abe0-47d5-89cb-f3a1e4318432.5aa06f62-4dc1-4331-a591-1cba6483a6f5?q=90&w=177&h=177",
		"uuid": "9PBVFGGXZV24",
		"platforms": [
			"Killing Time: Resurrected"
		]
	},
	{
		"name": "Killer Instinct: Anniversary Edition",
		"price": "$29.99",
		"image": "https://store-images.s-microsoft.com/image/apps.61867.13952178927417910.ff893240-27f8-4a82-baab-c24dbb3d822c.b65559b7-849b-4bfc-8d99-72bd1f8fc31c?q=90&w=177&h=177",
		"uuid": "9N2HB4MWG7HM",
		"platforms": [
			"Killer Instinct: Anniversary Edition"
		]
	},
	{
		"name": "Killer Frequency",
		"price": "$24.99",
		"image": "https://store-images.s-microsoft.com/image/apps.39696.13809628771831390.2a2afbac-b625-4651-bedf-8e3bbb751bbb.8357a5f7-e1c9-46e8-b2c7-ad818a40c744?q=90&w=177&h=177",
		"uuid": "9MTMSS84NW5R",
		"platforms": [
			"Killer Frequency"
		]
	},
	{
		"name": "Kona II: Brume",
		"price": "$29.99",
		"image": "https://store-images.s-microsoft.com/image/apps.34928.13844667147142160.362497bb-868e-416f-b78d-359043e116a5.5dd78fff-9af6-41e6-bbcd-6810d4c343b6?q=90&w=177&h=177",
		"uuid": "9MWG18BH5ML7",
		"platforms": [
			"Kona II: Brume"
		]
	},
	{
		"name": "Kerbal Space Program Enhanced Edition",
		"price": "$39.99+",
		"image": "https://store-images.s-microsoft.com/image/apps.52656.69605131994189608.186a980f-0738-4222-acd5-fb9c9ef32077.fa652e09-4deb-44de-a460-a8928361d50a?q=90&w=177&h=177",
		"uuid": "BRBD7BDK271P",
		"platforms": [
			"Kerbal Space Program Enhanced Edition"
		]
	},
	{
		"name": "Kane & Lynch 2",
		"price": "$14.99+",
		"image": "https://store-images.s-microsoft.com/image/apps.27943.66090267447566515.61271af5-be33-40a5-a102-433643651bb0.30c6a275-33ec-4a7e-97f8-fd0233b2b0b1?q=90&w=177&h=177",
		"uuid": "C3KNJV4PP1LD",
		"platforms": [
			"Kane & Lynch 2"
		]
	},
	{
		"name": "Kill It With Fire",
		"price": "$14.99+",
		"image": "https://store-images.s-microsoft.com/image/apps.12401.13862857064512538.2709e225-b83d-480b-aeaf-58a54a6a45bb.17dd9acd-bdb3-4201-9ec4-a5ff91f3344a?q=90&w=177&h=177",
		"uuid": "9MZVSHQZ666K",
		"platforms": [
			"Kill It With Fire"
		]
	},
	{
		"name": "Kunitsu-Gami: Path of the Goddess",
		"price": "$39.99+",
		"image": "https://store-images.s-microsoft.com/image/apps.51317.14165819607364549.40790d3a-f3e1-473e-81b4-61500e8b5087.a9264302-3ac6-4c93-a740-25d00ed0cf0a?q=90&w=177&h=177",
		"uuid": "9PCWXX0MS15S",
		"platforms": [
			"Kunitsu-Gami: Path of the Goddess"
		]
	},
	{
		"name": "King Kong",
		"price": "Free",
		"image": "https://store-images.s-microsoft.com/image/apps.12300.71957340853924373.94059fb7-9da8-49b0-9c17-c439da60a18c.ad20d60c-0167-4a3c-972b-6fbb1289a507?q=90&w=177&h=177",
		"uuid": "BWBDGLJTDCKS",
		"platforms": [
			"King Kong"
		]
	},
	{
		"name": "Korgan",
		"price": "Free+",
		"image": "https://store-images.s-microsoft.com/image/apps.47600.70110603074447323.b7a3e776-5182-4a29-a868-28a6e739f019.2943a1ea-6a44-474f-90ae-a5622636cc94?q=90&w=177&h=177",
		"uuid": "BS4R9GLTJBRL",
		"platforms": [
			"Korgan"
		]
	},
	{
		"name": "Kingdoms of Amalur: Re-Reckoning",
		"price": "$39.99+",
		"image": "https://store-images.s-microsoft.com/image/apps.2885.14396872445173076.fe063380-71f4-4e5c-8364-1fceec65d95b.fc73bfa1-3654-4449-a984-962a3ea0f31c?q=90&w=177&h=177",
		"uuid": "9NVCNM9DQ839",
		"platforms": [
			"Kingdoms of Amalur: Re-Reckoning"
		]
	},
	{
		"name": "Killer Klowns From Outer Space: Digital Deluxe Edition",
		"price": "$59.99+",
		"image": "https://store-images.s-microsoft.com/image/apps.61271.14095031826179169.e92e5744-4067-4659-af57-9d3d3593e92d.857d1d29-11ad-464a-b25b-b301e3e3576b?q=90&w=177&h=177",
		"uuid": "9P8BV9BZD7TD",
		"platforms": [
			"Killer Klowns From Outer Space: Digital Deluxe Edition"
		]
	},
	{
		"name": "Katana Kata",
		"price": "$14.99",
		"image": "https://store-images.s-microsoft.com/image/apps.33991.13599382028920585.405ddbcf-19a2-4e4d-a9da-d0f239899c15.31db7b02-e79b-4228-b329-8c71cb348787?q=90&w=177&h=177",
		"uuid": "9NF7Z70ZSZW0",
		"platforms": [
			"Katana Kata"
		]
	},
	{
		"name": "Killing Floor 3 Elite Nightfall Edition",
		"price": "Free",
		"image": "https://store-images.s-microsoft.com/image/apps.56218.13698464897242707.7573947b-2108-4f33-b39b-6c6f2d27e641.aee4cd28-f705-410e-91b1-f3ea8d509dab?q=90&w=177&h=177",
		"uuid": "9NM5ZW2G1F1B",
		"platforms": [
			"Killing Floor 3 Elite Nightfall Edition"
		]
	},
	{
		"name": "Kingdom Coronation Collection",
		"price": "$49.99",
		"image": "https://store-images.s-microsoft.com/image/apps.45480.13761374601421226.403ca6ac-dbc1-4bca-a79f-72dc6338c97b.7fad3c77-0122-4405-b389-54982f77dced?q=90&w=177&h=177",
		"uuid": "9NR4HDGNDBTR",
		"platforms": [
			"Kingdom Coronation Collection"
		]
	},
	{
		"name": "Killing Floor 2 - Ultimate Edition",
		"price": "$59.99+",
		"image": "https://store-images.s-microsoft.com/image/apps.5773.13878578914908955.253c8991-842c-4da0-b264-a7394f8e75c5.9d4ef99b-1c21-4cd6-89da-3fcf74f23212?q=90&w=177&h=177",
		"uuid": "9MZ9PFRP8N20",
		"platforms": [
			"Killing Floor 2 - Ultimate Edition"
		]
	},
	{
		"name": "Kona",
		"price": "$14.99",
		"image": "https://store-images.s-microsoft.com/image/apps.26216.63579060588016569.6eb380da-b190-4777-b70f-99fd2b3b8470.4fdfcee8-afa4-4fe9-aa20-2b9807c2c8a1?q=90&w=177&h=177",
		"uuid": "BXDSG249D6Q2",
		"platforms": [
			"Kona"
		]
	},
	{
		"name": "Kill It With Fire 2",
		"price": "Free",
		"image": "https://store-images.s-microsoft.com/image/apps.48954.13889690924508162.c3600ca6-dd1e-4db8-8c20-b1d66e134e1d.51d806c7-f2d1-4f66-8e10-ffe40e5c7f76?q=90&w=177&h=177",
		"uuid": "9MXHL3TT792F",
		"platforms": [
			"Kill It With Fire 2"
		]
	},
	{
		"name": "Keep Talking and Nobody Explodes",
		"price": "$14.99",
		"image": "https://store-images.s-microsoft.com/image/apps.14039.14375974149324937.a7b7d79a-6907-44c2-8aeb-cf40e6d0f575.ac878db1-19e0-4a0e-86fd-74daffb34775?q=90&w=177&h=177",
		"uuid": "9NS2PTV2WZGG",
		"platforms": [
			"Keep Talking and Nobody Explodes"
		]
	},
	{
		"name": "King of the Faridun Supporter Pack",
		"price": "$99.99+",
		"image": "https://store-images.s-microsoft.com/image/apps.47094.14325812094955697.6d57de48-e053-4992-938e-19eaf839168b.431df954-6ad3-4e92-b02e-1467216950f9?q=90&w=177&h=177",
		"uuid": "9PPF2TGP3BP0",
		"platforms": [
			"King of the Faridun Supporter Pack"
		]
	},
	{
		"name": "King's Quest™",
		"price": "Free+",
		"image": "https://store-images.s-microsoft.com/image/apps.1285.69783044208405594.c0d6ec4e-4329-4612-9ab1-ae690e394670.17b56e07-47d0-433d-b873-9f55f89ee109?q=90&w=177&h=177",
		"uuid": "BRMFLRV79C3H",
		"platforms": [
			"King's Quest™"
		]
	},
	{
		"name": "Kingdom Eighties",
		"price": "$11.99",
		"image": "https://store-images.s-microsoft.com/image/apps.17428.14276639340532911.ae2f7dcb-c2a2-4e3b-9bb7-39741b6e4481.05e46704-0edb-4a86-91be-d9aed39657fb?q=90&w=177&h=177",
		"uuid": "9PJRKNNFDN08",
		"platforms": [
			"Kingdom Eighties"
		]
	},
	{
		"name": "Kerbal Space Program Enhanced Edition Complete",
		"price": "$59.99+",
		"image": "https://store-images.s-microsoft.com/image/apps.14300.13629212517267479.12ca2729-fd93-40ce-9e88-cea9e80f22d4.0ccd53f9-4978-4bab-b79c-3c6a061c401e?q=90&w=177&h=177",
		"uuid": "9NHJVGWGQTBJ",
		"platforms": [
			"Kerbal Space Program Enhanced Edition Complete"
		]
	},
	{
		"name": "Karma: The Dark World",
		"price": "Free",
		"image": "https://store-images.s-microsoft.com/image/apps.50334.14116529162025759.7b2fe861-72ed-4bba-9bad-225f8d31f28b.125e21ca-6572-4c2c-9e8a-5944ebfc45bc?q=90&w=177&h=177",
		"uuid": "9PBTRH54WM9Q",
		"platforms": [
			"Karma: The Dark World"
		]
	},
	{
		"name": "Killing Floor 3 Deluxe Edition",
		"price": "Free",
		"image": "https://store-images.s-microsoft.com/image/apps.42139.14094687295864008.6d92d6f9-5213-4ae8-967b-5ccfa362f728.a415c4b7-8562-488c-9266-b5ad81b374c0?q=90&w=177&h=177",
		"uuid": "9P8CD1ZPKGPT",
		"platforms": [
			"Killing Floor 3 Deluxe Edition"
		]
	},
	{
		"name": "Katana ZERO",
		"price": "$14.99",
		"image": "https://store-images.s-microsoft.com/image/apps.24078.14626281141266720.a6ffd3c3-2d6f-45eb-bb55-ff946c8a842d.165b58dc-264b-424d-8bbe-1ddd81be5eec?q=90&w=177&h=177",
		"uuid": "9P6CVNVMK56R",
		"platforms": [
			"Katana ZERO"
		]
	},
	{
		"name": "Knight Squad 2",
		"price": "$14.99",
		"image": "https://store-images.s-microsoft.com/image/apps.7120.14043283618460869.37a53b15-6786-4c30-af59-8fa2b7581dba.8f281e96-5aa2-4048-ab0a-02dd9537b1bf?q=90&w=177&h=177",
		"uuid": "9N8KR1GM6V1X",
		"platforms": [
			"Knight Squad 2"
		]
	},
	{
		"name": "Kinect Sports Rivals",
		"price": "$29.99+",
		"image": "https://store-images.s-microsoft.com/image/apps.54128.69709337064206981.da5845d2-9032-40f0-8ad7-e1576c0f8271.fd6c589c-f855-49b7-bdd4-ecc5014a8ba8?q=90&w=177&h=177",
		"uuid": "BRHSML8030ZN",
		"platforms": [
			"Kinect Sports Rivals"
		]
	},
	{
		"name": "Kung Fu Duel",
		"price": "$3.99",
		"image": "https://store-images.s-microsoft.com/image/apps.27519.14500760154940675.1557cc13-c2ab-4fb7-8220-0751c3edd222.ef350413-f746-4cea-af5d-077729186823?q=90&w=177&h=177",
		"uuid": "9P1ST9PSS18J",
		"platforms": [
			"Kung Fu Duel"
		]
	},
	{
		"name": "King's Bounty II - Lord's Edition",
		"price": "Free",
		"image": "https://store-images.s-microsoft.com/image/apps.37366.13826900482567209.b3ee42aa-6c8b-4dd6-aa29-cf076f5c90b5.0dcb48a9-575e-407a-b5b7-89c65d818e46?q=90&w=177&h=177",
		"uuid": "9MSRZ7LBB0K0",
		"platforms": [
			"King's Bounty II - Lord's Edition"
		]
	},
	{
		"name": "King of Seas",
		"price": "$24.99",
		"image": "https://store-images.s-microsoft.com/image/apps.16087.14303239620145528.6d7fe8e0-b3de-4957-adec-55d16ec85db5.b8b54115-44e1-45f3-8868-7d7603151c96?q=90&w=177&h=177",
		"uuid": "9PM0R43HPSS7",
		"platforms": [
			"King of Seas"
		]
	},
	{
		"name": "KinnikuNeko: SUPER MUSCLE CAT",
		"price": "$17.99",
		"image": "https://store-images.s-microsoft.com/image/apps.62068.14505336511399806.440bac72-1772-43d0-a220-ad21ff362e48.caad5d3b-2faf-493e-ad80-5227de70ce5b?q=90&w=177&h=177",
		"uuid": "9P1KQX1Z4Q1M",
		"platforms": [
			"KinnikuNeko: SUPER MUSCLE CAT"
		]
	},
	{
		"name": "Kingdoms of Amalur: Reckoning",
		"price": "Free",
		"image": "https://store-images.s-microsoft.com/image/apps.7440.64087071388179996.6e3a521c-d8aa-48a4-9614-a373586d0a5e.1830b333-4815-41e8-95f0-33cb7b09c1ee?q=90&w=177&h=177",
		"uuid": "BZ78HXHCZD39",
		"platforms": [
			"Kingdoms of Amalur: Reckoning"
		]
	},
	{
		"name": "KEMCO RPG Selection Vol. 4",
		"price": "$39.99+",
		"image": "https://store-images.s-microsoft.com/image/apps.18481.13625403108665293.0eb82050-4f84-4a52-a532-f302925f1741.9ff025c7-7332-4cd1-bacb-646b1d4a0c3e?q=90&w=177&h=177",
		"uuid": "9NHJ2R55Z7TS",
		"platforms": [
			"KEMCO RPG Selection Vol. 4"
		]
	},
	{
		"name": "Kingdom Heritage Bundle",
		"price": "$24.99",
		"image": "https://store-images.s-microsoft.com/image/apps.52954.13887975954895204.8843be4c-f986-4514-bc7d-70c4b9ec7029.b516c486-a12e-47a1-88ef-7ba9d72166ed?q=90&w=177&h=177",
		"uuid": "9MXSWM4KWBCT",
		"platforms": [
			"Kingdom Heritage Bundle"
		]
	},
	{
		"name": "Killer Instinct Classic",
		"price": "Free",
		"image": "https://store-images.s-microsoft.com/image/apps.20311.63528887622500676.fdc76197-5251-4a9e-9ec7-94e0c39fc502.ca932205-8e08-4ba7-bf19-e5dd43400abc?q=90&w=177&h=177",
		"uuid": "BX8FPDDRCLWT",
		"platforms": [
			"Killer Instinct Classic"
		]
	},
	{
		"name": "Kholat",
		"price": "$19.99",
		"image": "https://store-images.s-microsoft.com/image/apps.8669.69522124860892078.599bef1e-dbf5-4ed5-bea5-85fee26650b9.7281b3a1-18ba-4bba-b789-032d5dbcae35?q=90&w=177&h=177",
		"uuid": "BS2P4JMZNPVT",
		"platforms": [
			"Kholat"
		]
	},
	{
		"name": "KLONOA Phantasy Reverie Series",
		"price": "Free",
		"image": "https://store-images.s-microsoft.com/image/apps.56776.14542437804758632.3f0b5d67-0caf-4d96-9fc0-f2abf2a1f206.6e2a6383-ab39-48af-9d0e-d91552cfdd42?q=90&w=177&h=177",
		"uuid": "9P3H56XNWWR9",
		"platforms": [
			"KLONOA Phantasy Reverie Series"
		]
	},
	{
		"name": "Keylocker",
		"price": "$19.99",
		"image": "https://store-images.s-microsoft.com/image/apps.15940.13847841958187786.6a1c6dc8-7156-4829-8043-acca39fbdd0b.7f746cb0-d5f1-4b52-bfd8-9e6ea0f720c5?q=90&w=177&h=177",
		"uuid": "9MW8T50Z9J3C",
		"platforms": [
			"Keylocker"
		]
	},
	{
		"name": "KURSK",
		"price": "$19.99",
		"image": "https://store-images.s-microsoft.com/image/apps.53425.13763734460785831.331a3d3e-1ba9-4dd6-b6a1-ccac21935e10.cd2e8d2e-a431-4ddc-82c1-04426374ea3b?q=90&w=177&h=177",
		"uuid": "9NR0JHG31V5V",
		"platforms": [
			"KURSK"
		]
	},
	{
		"name": "KEMCO RPG Selection Vol. 3",
		"price": "$39.99+",
		"image": "https://store-images.s-microsoft.com/image/apps.54904.13517430059469644.c6554722-a9c0-4e89-b7af-bc868db8caa1.e99002e5-ee2d-4d6c-8338-b025e1471d95?q=90&w=177&h=177",
		"uuid": "9NBH3ZV0J3QC",
		"platforms": [
			"KEMCO RPG Selection Vol. 3"
		]
	},
	{
		"name": "KOF2002UM",
		"price": "$9.99",
		"image": "https://store-images.s-microsoft.com/image/apps.64913.70614396782829787.14c569b4-4d5e-4d95-93be-0a1b85f5b824.e3f5ad46-2458-4a76-a48e-61614f943d18?q=90&w=177&h=177",
		"uuid": "BTX1PSX2MBF6",
		"platforms": [
			"KOF2002UM"
		]
	},
	{
		"name": "Kingdom: New Lands",
		"price": "$14.99",
		"image": "https://store-images.s-microsoft.com/image/apps.25142.66084178781808662.5cbdeec6-594f-44e2-ab1a-acbdbbe8e331.ba16bcfa-7f17-4da1-a1db-faa54823c4e3?q=90&w=177&h=177",
		"uuid": "C3L6F8GL5LJK",
		"platforms": [
			"Kingdom: New Lands"
		]
	},
	{
		"name": "Knight Squad",
		"price": "$14.99+",
		"image": "https://store-images.s-microsoft.com/image/apps.56155.69019489075777328.76d71961-e725-4f6e-829a-5850d4770b21.3b28eabe-29a1-4534-b384-4e21369dfaf7?q=90&w=177&h=177",
		"uuid": "BQ9C40MT0WWK",
		"platforms": [
			"Knight Squad"
		]
	},
	{
		"name": "KILLER IS DEAD",
		"price": "$19.99+",
		"image": "https://store-images.s-microsoft.com/image/apps.48447.68826627283221018.483f8d21-1347-41fd-982b-6dbba0d99e2d.f7cfa717-cd73-4abb-b466-707be28b1a0f?q=90&w=177&h=177",
		"uuid": "BQZW37W54ZZM",
		"platforms": [
			"KILLER IS DEAD"
		]
	},
	{
		"name": "KeyWe",
		"price": "$24.99+",
		"image": "https://store-images.s-microsoft.com/image/apps.22235.13861799223982773.7090fbb0-1020-489d-b852-1f9024bcc456.dab2b1cc-2a78-4044-8823-05254affd89b?q=90&w=177&h=177",
		"uuid": "9MVKZJ414SZX",
		"platforms": [
			"KeyWe"
		]
	},
	{
		"name": "Koh-Lanta",
		"price": "$24.99+",
		"image": "https://store-images.s-microsoft.com/image/apps.65436.13807496323961288.754db577-ed09-40c8-8ded-02e8378a35a2.6a85f82c-2b4a-4de3-910b-d4ba06629975?q=90&w=177&h=177",
		"uuid": "9MTJC6FZ0047",
		"platforms": [
			"Koh-Lanta"
		]
	},
	{
		"name": "Kung Fury: Street Rage - ULTIMATE EDITION",
		"price": "$19.99",
		"image": "https://store-images.s-microsoft.com/image/apps.39666.13855758695260887.2fb0b065-e9f5-4917-8b5e-020e9ef64654.7c9bec12-dff6-457e-9148-786dcb81190a?q=90&w=177&h=177",
		"uuid": "9MVNJ6HXNN5B",
		"platforms": [
			"Kung Fury: Street Rage - ULTIMATE EDITION"
		]
	},
	{
		"name": "Katamari Damacy REROLL",
		"price": "$29.99",
		"image": "https://store-images.s-microsoft.com/image/apps.20606.14040796541555081.1fba6c1a-f52f-42b2-9f8a-4d79177d99bf.59434595-f2cd-4875-abac-c50798696de2?q=90&w=177&h=177",
		"uuid": "9N8X6BC9P0CX",
		"platforms": [
			"Katamari Damacy REROLL"
		]
	},
	{
		"name": "Kitten Island (Xbox Series)",
		"price": "$4.99",
		"image": "https://store-images.s-microsoft.com/image/apps.13016.14078477229884568.4778aa26-ceff-4b58-9bf8-06c32b10142f.e39122ae-b705-49d5-9a8b-05516e86af17?q=90&w=177&h=177",
		"uuid": "9P8ZFRD4B16R",
		"platforms": [
			"Kitten Island (",
			"Xbox Series",
			")",
			"Xbox Series X|S",
			"Xbox Series One"
		]
	},
	{
		"name": "Kingdom Rush Frontiers",
		"price": "$9.99",
		"image": "https://store-images.s-microsoft.com/image/apps.57835.14363618405653505.5df575ad-dd98-435a-a8f9-181904c1efc8.d46480c3-05f8-4f9d-88a1-7e8fefe9e531?q=90&w=177&h=177",
		"uuid": "9NSPSNLV2XQL",
		"platforms": [
			"Kingdom Rush Frontiers"
		]
	},
	{
		"name": "Kitten Island (Xbox One+Xbox Series+Windows)",
		"price": "$10.99",
		"image": "https://store-images.s-microsoft.com/image/apps.13016.13529577602008427.7e141be5-3646-4fa9-a091-035c1ec03653.f87e444b-ec04-4c5b-850b-1da95cfcda1b?q=90&w=177&h=177",
		"uuid": "9N9MWD3DFW9V",
		"platforms": [
			"Kitten Island (",
			"Xbox",
			" One+",
			"Xbox Series",
			"+",
			"Windows",
			")",
			"Xbox Series X|S",
			"Xbox Series One",
			"Cloud"
		]
	},
	{
		"name": "Kingdom Rush",
		"price": "$9.99",
		"image": "https://store-images.s-microsoft.com/image/apps.24293.14576301905573821.bc76c64b-3901-4a77-9bca-c920532ada73.9292ce2f-3734-4e3c-a0fa-ec1303fb9ea9?q=90&w=177&h=177",
		"uuid": "9P541N3KWMWD",
		"platforms": [
			"Kingdom Rush"
		]
	},
	{
		"name": "Kameo",
		"price": "Free",
		"image": "https://store-images.s-microsoft.com/image/apps.5299.68217578810932850.d232e670-e28b-4aa4-8b23-1a68089676d4.1acda38f-6ff6-4e71-bec9-4ec000cf3645?q=90&w=177&h=177",
		"uuid": "BPVP56VRVLZ7",
		"platforms": [
			"Kameo"
		]
	},
	{
		"name": "KOF98UM",
		"price": "$9.99",
		"image": "https://store-images.s-microsoft.com/image/apps.44787.64778072665897661.5dd96cdc-1f47-42a7-bb63-f2ed9da8c6c8.14c32b93-8364-4b37-ab69-575f151de236?q=90&w=177&h=177",
		"uuid": "C1D89J1G0NX2",
		"platforms": [
			"KOF98UM"
		]
	},
	{
		"name": "Kingdom Two Crowns: Olympus Edition",
		"price": "$25.99",
		"image": "https://store-images.s-microsoft.com/image/apps.17798.13877875279240967.3f07678f-5f86-43be-a1dc-afd7d9534968.bc55d0bf-fabb-4ca3-9c82-ec7fd110a2ce?q=90&w=177&h=177",
		"uuid": "9MZ3LCM4503G",
		"platforms": [
			"Kingdom Two Crowns: Olympus Edition"
		]
	},
	{
		"name": "Kingdom Two Crowns: Essentials Pack",
		"price": "$29.99",
		"image": "https://store-images.s-microsoft.com/image/apps.18147.14033007435017059.a1410b28-4cf2-42fd-8131-6fc895203a83.d662c3d5-0356-4486-b112-5d2f718a9cde?q=90&w=177&h=177",
		"uuid": "9N5R5WDJH4B0",
		"platforms": [
			"Kingdom Two Crowns: Essentials Pack"
		]
	},
	{
		"name": "Kingdom Imperial Collection",
		"price": "$39.99",
		"image": "https://store-images.s-microsoft.com/image/apps.22532.14110038791587770.cd14d66e-cf5f-4fd7-9b0b-6a9ff062f215.89a5339c-0640-4200-9adc-a7cbf281596c?q=90&w=177&h=177",
		"uuid": "9PBXFHHSLG2T",
		"platforms": [
			"Kingdom Imperial Collection"
		]
	},
	{
		"name": "King of the Arcade",
		"price": "$7.99",
		"image": "https://store-images.s-microsoft.com/image/apps.44561.13783221637780683.2d24fc86-fce1-49fe-b9c8-43e1ae375363.22724161-9ecf-4f9a-87ad-e4d57823d8f9?q=90&w=177&h=177",
		"uuid": "9NQ0RTGTTBWL",
		"platforms": [
			"King of the Arcade"
		]
	},
	{
		"name": "Kaichu: The Kaiju Dating Sim",
		"price": "$9.99",
		"image": "https://store-images.s-microsoft.com/image/apps.2443.13880058218333833.1cc94f92-27fa-4db6-947d-2d9907757203.80b931ad-8a01-46d6-933a-3f93633f9b4d?q=90&w=177&h=177",
		"uuid": "9MZ6X33K238L",
		"platforms": [
			"Kaichu: The Kaiju Dating Sim"
		]
	},
	{
		"name": "Kaze and the Wild Masks",
		"price": "$19.99+",
		"image": "https://store-images.s-microsoft.com/image/apps.63588.14100916894253934.f6c9c4b5-94a7-4369-a67a-c15376e6c09f.03b8e8be-f824-4dbd-b74e-43e3e35d2f44?q=90&w=177&h=177",
		"uuid": "9P7TK3GJVH57",
		"platforms": [
			"Kaze and the Wild Masks"
		]
	},
	{
		"name": "King's Quest™ : The Complete Collection",
		"price": "$29.99+",
		"image": "https://store-images.s-microsoft.com/image/apps.36076.67040529145279171.5fc71eba-6f8d-4e3e-97ef-c1ef58f86609.0787f26f-94e2-465e-a133-6e1288e91218?q=90&w=177&h=177",
		"uuid": "C55WG3PP53MQ",
		"platforms": [
			"King's Quest™ : The Complete Collection"
		]
	},
	{
		"name": "Krampus Kills",
		"price": "$14.99",
		"image": "https://store-images.s-microsoft.com/image/apps.58470.14307309435488158.52037a9e-f37c-4363-b8d2-fd1a419e9676.16eb538e-fae3-4923-932f-9a45e4cdda57?q=90&w=177&h=177",
		"uuid": "9PLSLJTGX8TC",
		"platforms": [
			"Krampus Kills"
		]
	},
	{
		"name": "King's Bounty II",
		"price": "$39.99+",
		"image": "https://store-images.s-microsoft.com/image/apps.49096.14433676622326754.f01a74c7-b209-4264-aa58-017099488453.71bb5f40-359b-4e65-8783-1a87637ead96?q=90&w=177&h=177",
		"uuid": "9NX9732PK1R7",
		"platforms": [
			"King's Bounty II"
		]
	},
	{
		"name": "KEMCO RPG Selection Vol. 2",
		"price": "$39.99+",
		"image": "https://store-images.s-microsoft.com/image/apps.14162.13687713642591724.1d680d51-b3c5-4a90-a231-f6133ec0e543.8b5b16df-56a1-49cd-9888-d76a16df220e?q=90&w=177&h=177",
		"uuid": "9NMHK7T44J8W",
		"platforms": [
			"KEMCO RPG Selection Vol. 2"
		]
	},
	{
		"name": "Kamaeru: A Frog Refuge",
		"price": "$19.99",
		"image": "https://store-images.s-microsoft.com/image/apps.58948.13619990393632060.dfb57c58-c4ac-4c3d-adac-9d49f35e869c.aad4a7fb-0bb3-4e42-9d54-d71f9f5bc649?q=90&w=177&h=177",
		"uuid": "9NJ0NC3VVJJC",
		"platforms": [
			"Kamaeru: A Frog Refuge"
		]
	},
	{
		"name": "Knights and Bikes",
		"price": "$19.99",
		"image": "https://store-images.s-microsoft.com/image/apps.32092.14631376149189004.de7c846f-fe64-4f51-81bc-3f1402a429e5.83894d7d-998d-4136-91d7-f8faf72c0451?q=90&w=177&h=177",
		"uuid": "9P64KV1HQK07",
		"platforms": [
			"Knights and Bikes"
		]
	},
	{
		"name": "Kentucky Route Zero: TV Edition",
		"price": "$24.99",
		"image": "https://store-images.s-microsoft.com/image/apps.12186.14620558670939884.b282563f-ef8a-4a4d-8cd6-6780477a8cf6.661c5892-e5d4-40d3-973b-8431fe499724?q=90&w=177&h=177",
		"uuid": "9P6FTM76L1S7",
		"platforms": [
			"Kentucky Route Zero: TV Edition"
		]
	},
	{
		"name": "Knights of Grayfang",
		"price": "$14.99+",
		"image": "https://store-images.s-microsoft.com/image/apps.26544.13937375854174018.14e05563-d6bc-4c46-851e-0f714e92c779.69337a97-ab4a-4744-8084-c5b8b939d0d1?q=90&w=177&h=177",
		"uuid": "9N3GJKS8KC6F",
		"platforms": [
			"Knights of Grayfang"
		]
	},
	{
		"name": "Kung-Fu for Kinect",
		"price": "$19.99+",
		"image": "https://store-images.s-microsoft.com/image/apps.58932.70943897529201295.ba759173-21fe-4cbc-8d9c-718d37c3567c.756d9218-bb7d-47c4-be78-cfcae6ea22cf?q=90&w=177&h=177",
		"uuid": "BVK1LRW59L64",
		"platforms": [
			"Kung-Fu for Kinect"
		]
	},
	{
		"name": "KLONOA Phantasy Reverie Series: Special Bundle",
		"price": "$19.99",
		"image": "https://store-images.s-microsoft.com/image/apps.18152.14065803436132348.44eb9afc-a404-40e4-9f27-daa1f97bd42c.18916db5-5fff-48c1-be8c-cfa89188c7cf?q=90&w=177&h=177",
		"uuid": "9N7FCQXSNWC5",
		"platforms": [
			"KLONOA Phantasy Reverie Series: Special Bundle"
		]
	},
	{
		"name": "Kaiju Wars",
		"price": "$19.99",
		"image": "https://store-images.s-microsoft.com/image/apps.12314.13606727059141356.47c54325-1a67-4425-a155-05864c041db8.26842558-c486-47b4-9844-9adcbec23e8b?q=90&w=177&h=177",
		"uuid": "9NF41QZPCGZP",
		"platforms": [
			"Kaiju Wars"
		]
	},
	{
		"name": "Kemono Heroes",
		"price": "$14.99",
		"image": "https://store-images.s-microsoft.com/image/apps.40754.13733090277642558.16cbeab5-c16e-4f82-ac67-27d3cfe026f6.c40d64e6-f8fa-41b1-bab7-eec2a51ea142?q=90&w=177&h=177",
		"uuid": "9NP0G7STW76K",
		"platforms": [
			"Kemono Heroes"
		]
	},
	{
		"name": "Knight vs Giant: The Broken Excalibur",
		"price": "$19.99",
		"image": "https://store-images.s-microsoft.com/image/apps.16376.14269562917511497.88076403-aac2-4bba-af10-711cf02fa0c0.efa06ac4-166c-4a37-b230-ec03a954256b?q=90&w=177&h=177",
		"uuid": "9PKC29DP3MSV",
		"platforms": [
			"Knight vs Giant: The Broken Excalibur"
		]
	},
	{
		"name": "Kovox Pitch",
		"price": "$6.99",
		"image": "https://store-images.s-microsoft.com/image/apps.26755.13981848354243934.8460fb0c-5ba4-4e3f-94c2-4ef49ce28383.612b8054-b05f-4ede-bb2b-4955f4967479?q=90&w=177&h=177",
		"uuid": "9N4K9J8W6P3C",
		"platforms": [
			"Kovox Pitch"
		]
	},
	{
		"name": "KEMCO RPG Selection Vol. 1",
		"price": "$39.99+",
		"image": "https://store-images.s-microsoft.com/image/apps.39010.14566478140788736.92be634f-aec5-44e5-afa2-b4bc5f10fe43.ddf34dd7-4715-4349-b2bb-281ba3a1ec97?q=90&w=177&h=177",
		"uuid": "9P5MFG9SBG9K",
		"platforms": [
			"KEMCO RPG Selection Vol. 1"
		]
	},
	{
		"name": "Kitten Island",
		"price": "$4.99",
		"image": "https://store-images.s-microsoft.com/image/apps.13016.14387699687528269.6461eff0-075b-486c-b768-20b397e56021.36e15680-bd12-4cff-a6af-5472d31a3898?q=90&w=177&h=177",
		"uuid": "9NR832T55HJ6",
		"platforms": [
			"Kitten Island"
		]
	},
	{
		"name": "Kitty Powers' Matchmaker",
		"price": "$9.99",
		"image": "https://store-images.s-microsoft.com/image/apps.37730.65431837931183080.7f48110e-9cd1-4a9e-ba08-7fd1174a3e70.7951cc1b-ec24-4c68-8cd2-6784935001d0?q=90&w=177&h=177",
		"uuid": "C2F67LCVGF8W",
		"platforms": [
			"Kitty Powers' Matchmaker"
		]
	},
	{
		"name": "KEMCO RPG Selection Vol. 5",
		"price": "$39.99+",
		"image": "https://store-images.s-microsoft.com/image/apps.28199.14443692016682121.5759a249-f830-47ca-9c62-f68301ef57c6.794be1e9-95a7-4c45-a37c-a7a6b99788b5?q=90&w=177&h=177",
		"uuid": "9NWKLZT5R7VG",
		"platforms": [
			"KEMCO RPG Selection Vol. 5"
		]
	},
	{
		"name": "KungFu Kickball",
		"price": "$19.99",
		"image": "https://store-images.s-microsoft.com/image/apps.58953.14017563413824424.68a404c2-6850-4376-a8c0-35fcf451731c.cbddc97f-5483-4876-920b-4451a2e2984c?q=90&w=177&h=177",
		"uuid": "9N6B2HB2C9XW",
		"platforms": [
			"KungFu Kickball"
		]
	},
	{
		"name": "Knights of Braveland",
		"price": "$19.99+",
		"image": "https://store-images.s-microsoft.com/image/apps.3673.13815631544437030.fb66875c-8667-4e6c-bc63-4fcd1724527c.474215b3-a3f1-4b9a-9de6-42f42d0fd0e9?q=90&w=177&h=177",
		"uuid": "9MT4FDMPGXHH",
		"platforms": [
			"Knights of Braveland"
		]
	},
	{
		"name": "KOF SKY STAGE",
		"price": "$9.99",
		"image": "https://store-images.s-microsoft.com/image/apps.56822.65787581711623022.7e782fc6-b928-4ad7-b301-7a4f11ed0388.6b042924-54e6-4049-b0ce-3d97afac48ec?q=90&w=177&h=177",
		"uuid": "C228GX7BRJM7",
		"platforms": [
			"KOF SKY STAGE"
		]
	},
	{
		"name": "Kamikaze Veggies",
		"price": "$12.99",
		"image": "https://store-images.s-microsoft.com/image/apps.39383.13988520670120121.ce2a6713-99e8-4b6f-9cb9-83b0c7238cf8.65225a7d-2d15-4090-abda-7f65b717afa1?q=90&w=177&h=177",
		"uuid": "9N4FW3XF7TL6",
		"platforms": [
			"Kamikaze Veggies"
		]
	},
	{
		"name": "King of Meat",
		"price": "Free",
		"image": "https://store-images.s-microsoft.com/image/apps.28095.14332257470543384.6c29cd9c-0ab3-4314-a09d-64977fad1733.c365be3a-226b-4fda-824e-ff9ee002c424?q=90&w=177&h=177",
		"uuid": "9PPB3ZRFG3R1",
		"platforms": [
			"King of Meat"
		]
	},
	{
		"name": "Kiting Cat",
		"price": "$4.99",
		"image": "https://store-images.s-microsoft.com/image/apps.12745.13531618922776018.fc187b09-96f0-4001-8ea8-ae6e83b0ba90.937d7a44-4263-417d-b279-86dd0d0675f5?q=90&w=177&h=177",
		"uuid": "9N9S0V84DTZC",
		"platforms": [
			"Kiting Cat"
		]
	},
	{
		"name": "Kingdom Treasury Collection",
		"price": "$29.99+",
		"image": "https://store-images.s-microsoft.com/image/apps.37218.66996871674833063.daaba571-3335-4b1d-9f17-569a15e4b51b.ffd2b8b4-30bc-4544-9946-41a3e45e0714?q=90&w=177&h=177",
		"uuid": "C54JWFXKT65B",
		"platforms": [
			"Kingdom Treasury Collection"
		]
	},
	{
		"name": "Kitaria Fables",
		"price": "$19.99+",
		"image": "https://store-images.s-microsoft.com/image/apps.22209.13581323322213142.ed2e0b70-79ff-4c63-9f88-05a049d16efe.a312e42e-c315-4bdd-a4ce-29c092e7ec4a?q=90&w=177&h=177",
		"uuid": "9NG5Z2VVTXJ9",
		"platforms": [
			"Kitaria Fables"
		]
	},
	{
		"name": "Kao the Kangaroo",
		"price": "$29.99+",
		"image": "https://store-images.s-microsoft.com/image/apps.50076.14550840516243157.2925768c-6be9-4262-bfb2-eb396cba64cc.59bd40f9-f28e-4afa-a27f-44c36f9a2172?q=90&w=177&h=177",
		"uuid": "9P2V402QXH62",
		"platforms": [
			"Kao the Kangaroo"
		]
	},
	{
		"name": "Knee Deep",
		"price": "$14.99",
		"image": "https://store-images.s-microsoft.com/image/apps.14226.64750991529798362.1eb0d61b-124f-4a8b-ac85-2e58dfbba1d3.bafa9098-0803-4369-8f59-b95f4f731a35?q=90&w=177&h=177",
		"uuid": "C1B2WH2W401H",
		"platforms": [
			"Knee Deep"
		]
	},
	{
		"name": "Knights of Pen & Paper 2 Deluxiest Edition",
		"price": "$12.99",
		"image": "https://store-images.s-microsoft.com/image/apps.40808.14144265807510800.6bf68dc9-a361-4eb5-89be-5af753d75710.9543d241-686b-4fc3-b36e-7828916094ec?q=90&w=177&h=177",
		"uuid": "9PDRXL65SPMT",
		"platforms": [
			"Knights of Pen & Paper 2 Deluxiest Edition"
		]
	},
	{
		"name": "Ken Follett's The Pillars of the Earth",
		"price": "$19.99",
		"image": "https://store-images.s-microsoft.com/image/apps.15647.70132717725160587.05ef70c7-7a25-4949-80eb-9e73946d925b.a70f96f5-b481-42da-86b6-4fa953220d0f?q=90&w=177&h=177",
		"uuid": "BS76CQL5FZS0",
		"platforms": [
			"Ken Follett's The Pillars of the Earth"
		]
	},
	{
		"name": "King of the Hat",
		"price": "$19.99",
		"image": "https://store-images.s-microsoft.com/image/apps.53007.13715859518904445.69b834d8-0e69-4a21-b5fc-b038181eab4a.f7e37cb9-ca00-44fc-957e-7bd1718a81cb?q=90&w=177&h=177",
		"uuid": "9NL8W7NXWHBB",
		"platforms": [
			"King of the Hat"
		]
	},
	{
		"name": "Klabater Bundle: The Amazing American Circus, Moonshine Inc., Heliborne and Crossroads Inn",
		"price": "$79.99+",
		"image": "https://store-images.s-microsoft.com/image/apps.3383.13675570499198499.46b29de3-c221-46b9-95ef-3155586a86b1.30446b13-10c1-452e-8a4a-3c19fdf944fd?q=90&w=177&h=177",
		"uuid": "9NJJFW6T33WQ",
		"platforms": [
			"Klabater Bundle: The Amazing American Circus, Moonshine Inc., Heliborne and Crossroads Inn"
		]
	},
	{
		"name": "Kraken Academy!!",
		"price": "$17.99",
		"image": "https://store-images.s-microsoft.com/image/apps.17451.14093132429705053.80d7d0ce-fb78-4b3f-85e0-84bfb558041a.8594517f-cfdd-4bc2-a491-787adebd921c?q=90&w=177&h=177",
		"uuid": "9P87CGF1TCCX",
		"platforms": [
			"Kraken Academy!!"
		]
	},
	{
		"name": "Koa and the Five Pirates of Mara",
		"price": "$19.99",
		"image": "https://store-images.s-microsoft.com/image/apps.41060.14455986913345903.c9ba3d95-a004-41fa-9cd6-f80aee0e137f.bd89c7fc-cf90-4c82-b067-10e6dd06af62?q=90&w=177&h=177",
		"uuid": "9NW5KZ01QG5V",
		"platforms": [
			"Koa and the Five Pirates of Mara"
		]
	},
	{
		"name": "KarmaZoo",
		"price": "$9.99",
		"image": "https://store-images.s-microsoft.com/image/apps.7667.14069106766541599.81c7e3a5-ed66-492c-b5f9-441f750ed3ad.6fc888ed-8276-41b2-b0d6-6a28eaab534e?q=90&w=177&h=177",
		"uuid": "9N7H1V8CT8T2",
		"platforms": [
			"KarmaZoo"
		]
	},
	{
		"name": "Kill The Bad Guy",
		"price": "$6.99",
		"image": "https://store-images.s-microsoft.com/image/apps.32207.69096850931399758.375d781b-a9ba-44c2-bad1-906e7a171bd9.c891ecc8-b18a-4d7a-9ed6-243cae77b690?q=90&w=177&h=177",
		"uuid": "BQDSRXRC1K57",
		"platforms": [
			"Kill The Bad Guy"
		]
	},
	{
		"name": "Kraken Odyssey",
		"price": "$14.99",
		"image": "https://store-images.s-microsoft.com/image/apps.33818.14118367504555002.dc56c18d-59bb-4036-a440-8aed54d318ae.15a7730d-a32c-4537-b8e5-f46270611eb8?q=90&w=177&h=177",
		"uuid": "9PBHS6HQSLKR",
		"platforms": [
			"Kraken Odyssey"
		]
	},
	{
		"name": "Kara Fantasy",
		"price": "$5.99",
		"image": "https://store-images.s-microsoft.com/image/apps.28134.13631335205676433.9244bc37-c6eb-4f4b-8f21-3a02201c32cd.582c483f-7ce1-4585-8066-38dbb304d0ac?q=90&w=177&h=177",
		"uuid": "9NH6XBB1BW0B",
		"platforms": [
			"Kara Fantasy"
		]
	},
	{
		"name": "Krimson",
		"price": "$9.99",
		"image": "https://store-images.s-microsoft.com/image/apps.49698.14141454137534667.14a85134-3928-424b-bb0a-eacc31031bbb.68b5a056-253c-4621-a6c3-0d659c9ec2b4?q=90&w=177&h=177",
		"uuid": "9P9BK0DGVGXX",
		"platforms": [
			"Krimson"
		]
	},
	{
		"name": "Kingdom Of Explorers",
		"price": "Free",
		"image": "https://store-images.s-microsoft.com/image/apps.3936.14235288912710046.2008a84d-86d2-46fc-aa5a-eb0cee715e3b.175c090d-b836-4204-8b68-5387f94ef6d0?q=90&w=177&h=177",
		"uuid": "9PHJJ2745G4K",
		"platforms": [
			"Kingdom Of Explorers"
		]
	},
	{
		"name": "Kalinur",
		"price": "$5.99",
		"image": "https://store-images.s-microsoft.com/image/apps.7321.13624457043228774.344fa461-2598-4cc4-bd57-badf074ab3ca.3ab1867a-93af-4eb9-bc1e-1858287e2bb3?q=90&w=177&h=177",
		"uuid": "9NHRV2HKM5HM",
		"platforms": [
			"Kalinur"
		]
	},
	{
		"name": "Knights of Pen and Paper +1 Deluxier Edition",
		"price": "$14.99",
		"image": "https://store-images.s-microsoft.com/image/apps.18082.14533795925713926.a066a767-2957-4628-b09a-d7508d7d17f6.26cede1a-365d-4509-a3dd-e0a0bc80a5af?q=90&w=177&h=177",
		"uuid": "9P3XSG3180NT",
		"platforms": [
			"Knights of Pen and Paper +1 Deluxier Edition"
		]
	},
	{
		"name": "Keeper's Toll",
		"price": "Free",
		"image": "https://store-images.s-microsoft.com/image/apps.489.13891073462674333.5b3e7078-6455-43e0-9fe0-07f1e4514997.991b57a3-e3e0-4f85-9ce2-fb2a64214835?q=90&w=177&h=177",
		"uuid": "9MXFGTP6P29D",
		"platforms": [
			"Keeper's Toll"
		]
	},
	{
		"name": "Kitaria Fables: Deluxe Edition",
		"price": "$24.99+",
		"image": "https://store-images.s-microsoft.com/image/apps.4097.13717512858822682.f20cecfb-4641-42e9-a604-72d9e64b9d2d.28d0a61c-8491-4fac-94e3-c206a947267a?q=90&w=177&h=177",
		"uuid": "9NKZNH426QT7",
		"platforms": [
			"Kitaria Fables: Deluxe Edition"
		]
	},
	{
		"name": "King Leo",
		"price": "$14.99",
		"image": "https://store-images.s-microsoft.com/image/apps.31218.14113933624577871.c226eadd-0d2c-447f-bd97-a73a8a91deb0.b8f40f93-ec67-4c78-8c0b-df11ab01e48e?q=90&w=177&h=177",
		"uuid": "9PBQN2MS4X1V",
		"platforms": [
			"King Leo"
		]
	},
	{
		"name": "Kinect Mega Bundle: 4 in 1",
		"price": "$49.99+",
		"image": "https://store-images.s-microsoft.com/image/apps.33132.67451774254048402.32a3f2d2-7745-4d6f-97a7-9f895ae546a2.c5f926b6-9aad-4c12-a77c-c40bdfeb5793?q=90&w=177&h=177",
		"uuid": "C4ZJGMMWGNK7",
		"platforms": [
			"Kinect Mega Bundle: 4 in 1"
		]
	},
	{
		"name": "Kiki - A Vibrant 3D Platformer",
		"price": "$4.99",
		"image": "https://store-images.s-microsoft.com/image/apps.28082.14363964442665224.6291c526-8b9b-4a6e-912a-667274a63814.f3497449-0ee0-47a7-828f-132f429d90ea?q=90&w=177&h=177",
		"uuid": "9NSP8TWS4PCK",
		"platforms": [
			"Kiki - A Vibrant 3D Platformer"
		]
	},
	{
		"name": "King's Heir: Rise to the Throne (Xbox One Version)",
		"price": "$14.99",
		"image": "https://store-images.s-microsoft.com/image/apps.53613.71110693695812663.4176a66b-6471-4a5c-978d-64e7dcd2de07.959ba800-ec1a-4818-93ca-dcd148864d3d?q=90&w=177&h=177",
		"uuid": "BVVFPLQNSWG0",
		"platforms": [
			"King's Heir: Rise to the Throne (",
			"Xbox",
			" One Version)"
		]
	},
	{
		"name": "Knight And Mourning",
		"price": "$1.59",
		"image": "https://store-images.s-microsoft.com/image/apps.50837.13871290757715699.4e3a1094-b11a-4a2a-a837-401a2181f21d.6513bdee-69be-4e9f-a126-26044cc13c3a?q=90&w=177&h=177",
		"uuid": "9MZND2PSGBP6",
		"platforms": [
			"Knight And Mourning"
		]
	},
	{
		"name": "Kine",
		"price": "$19.99",
		"image": "https://store-images.s-microsoft.com/image/apps.34412.13644284251211225.7cddef83-f0d7-4f54-a61c-78fc1edbc4a5.192fc492-5298-433e-87cb-35f4afeb55b7?q=90&w=177&h=177",
		"uuid": "9NGK7V4RRR9X",
		"platforms": [
			"Kine"
		]
	},
	{
		"name": "Kao the Kangaroo: Anniversary Edition",
		"price": "$36.99+",
		"image": "https://store-images.s-microsoft.com/image/apps.2893.13647923553999171.4095bd7e-05eb-4a86-a07c-4f563560d342.9c382b9b-a8a9-4fb8-ad99-58f8d73851a1?q=90&w=177&h=177",
		"uuid": "9NGCPDC7XD28",
		"platforms": [
			"Kao the Kangaroo: Anniversary Edition"
		]
	},
	{
		"name": "Kick it, Bunny!",
		"price": "$9.99",
		"image": "https://store-images.s-microsoft.com/image/apps.15680.13896053031703936.8696552c-1afe-4108-b6a2-a0384ee43fb4.4caf3577-d0a1-49aa-af26-750719b71374?q=90&w=177&h=177",
		"uuid": "9MXDWQ7G5JX7",
		"platforms": [
			"Kick it, Bunny!"
		]
	},
	{
		"name": "Knights of Braveland - Ultimate Edition",
		"price": "$44.99+",
		"image": "https://store-images.s-microsoft.com/image/apps.58429.13681515462502057.db4fb402-1c1f-421c-a914-474f3986e2c9.c145bd4f-2edb-4285-b0ec-cf4fe3ffa3b4?q=90&w=177&h=177",
		"uuid": "9NJG1JSBL55N",
		"platforms": [
			"Knights of Braveland - Ultimate Edition"
		]
	},
	{
		"name": "Kitten Hero",
		"price": "$4.99",
		"image": "https://store-images.s-microsoft.com/image/apps.60251.14570393162473131.438a7633-525a-4257-b148-1b82d1292e85.6126c4b9-ca52-4e10-874b-4add137198c5?q=90&w=177&h=177",
		"uuid": "9P5N5HL106G0",
		"platforms": [
			"Kitten Hero"
		]
	},
	{
		"name": "Kao the Kangaroo A Well Good Bundle",
		"price": "$32.99+",
		"image": "https://store-images.s-microsoft.com/image/apps.37251.13649679592059930.47d71178-f514-44c5-af13-1997d0e9c9f7.d62da930-a396-417f-be67-b895f5a343af?q=90&w=177&h=177",
		"uuid": "9NGHDTCVDBWC",
		"platforms": [
			"Kao the Kangaroo A Well Good Bundle"
		]
	},
	{
		"name": "Kaiju Panic",
		"price": "$15.99",
		"image": "https://store-images.s-microsoft.com/image/apps.58336.64270104309869956.c64b27f4-481d-401c-80d1-8a1df53e9d1a.46bcc430-a336-4fc7-b387-4e8a4f56ae91?q=90&w=177&h=177",
		"uuid": "C0G7183W6WCF",
		"platforms": [
			"Kaiju Panic"
		]
	},
	{
		"name": "Kombinera",
		"price": "$14.99",
		"image": "https://store-images.s-microsoft.com/image/apps.21343.13852617208921502.fffdaa00-9726-456d-99de-f48dc0575022.6d31ae94-19a2-491f-8abe-3f0ef52b1088?q=90&w=177&h=177",
		"uuid": "9MW1V5ZTJTNF",
		"platforms": [
			"Kombinera"
		]
	},
	{
		"name": "Kansei: The Second Turn HD",
		"price": "$7.99",
		"image": "https://store-images.s-microsoft.com/image/apps.3931.13909192176484554.0c05bba0-1470-4da4-9a11-645f0efd0722.4c73d1d2-5b9c-451f-8ff9-b9139e022608?q=90&w=177&h=177",
		"uuid": "9N19RJK9K06K",
		"platforms": [
			"Kansei: The Second Turn HD"
		]
	},
	{
		"name": "Kid Ball Adventure",
		"price": "$4.99",
		"image": "https://store-images.s-microsoft.com/image/apps.32237.14518125978344527.15d2308e-ab7c-4bd7-a357-9218bd2d519d.398aafc2-38f7-4802-b776-d388171bd085?q=90&w=177&h=177",
		"uuid": "9P0XQ8GJBFPG",
		"platforms": [
			"Kid Ball Adventure"
		]
	},
	{
		"name": "KickBeat Special Edition",
		"price": "$9.99",
		"image": "https://store-images.s-microsoft.com/image/apps.47267.68624034650477545.c56aca38-a784-441e-94d9-6a82cd1702cb.7d944087-7727-4553-b4aa-72554fa59cde?q=90&w=177&h=177",
		"uuid": "BPN4BFRVKGCN",
		"platforms": [
			"KickBeat Special Edition"
		]
	},
	{
		"name": "Kingdom of Arcadia",
		"price": "$5.99",
		"image": "https://store-images.s-microsoft.com/image/apps.7510.13777510134602539.5b80f555-476f-4e76-95f2-395411ac3e97.ab137b50-8cfa-438d-a503-03cc5511c733?q=90&w=177&h=177",
		"uuid": "9NQ9FF200J4N",
		"platforms": [
			"Kingdom of Arcadia"
		]
	},
	{
		"name": "KALIMBA",
		"price": "$9.99+",
		"image": "https://store-images.s-microsoft.com/image/apps.43257.65797690556719461.d7adc74a-94bb-4275-a019-c776d63c7c38.c2eb0512-23a6-40bc-8885-61df750bc80d?q=90&w=177&h=177",
		"uuid": "C25K1D8B4H2B",
		"platforms": [
			"KALIMBA"
		]
	},
	{
		"name": "Kinect Bundle: Boom Ball 2 + Squid Hero",
		"price": "$18.99",
		"image": "https://store-images.s-microsoft.com/image/apps.62422.70993125176366168.7a9610c5-2c45-4532-ac24-f946aa154f62.b282b59f-0f1b-4ca7-b223-5aad93d57756?q=90&w=177&h=177",
		"uuid": "BVL3W1CB93P5",
		"platforms": [
			"Kinect Bundle: Boom Ball 2 + Squid Hero"
		]
	},
	{
		"name": "Klang 2",
		"price": "$14.99",
		"image": "https://store-images.s-microsoft.com/image/apps.11790.13705230270870825.40e89825-777c-43f9-93ba-40c81a8fdde6.2c886cca-16a6-4768-928f-30946c910907?q=90&w=177&h=177",
		"uuid": "9NLLFP0PLRT4",
		"platforms": [
			"Klang 2"
		]
	},
	{
		"name": "Knowledge Keeper (Xbox Series X|S)",
		"price": "$4.99",
		"image": "https://store-images.s-microsoft.com/image/apps.59265.14207261322119456.23cdc613-7528-4397-93f9-b20a49708c18.d293deb6-52a3-486f-bd4e-fda9a1b9de79?q=90&w=177&h=177",
		"uuid": "9PF5BFWQ539P",
		"platforms": [
			"Knowledge Keeper (",
			"Xbox Series",
			" X|S)",
			"Xbox Series X|S",
			"Xbox Series One"
		]
	},
	{
		"name": "Kaiju Wars + Legend of Keepers - Monsters & Demons Deluxe Bundle",
		"price": "$41.99+",
		"image": "https://store-images.s-microsoft.com/image/apps.35384.14619008324321761.3dc13978-c790-4a6f-a992-06cbfd66f266.c9c451e5-871c-4b1d-a7b5-4ac30786279d?q=90&w=177&h=177",
		"uuid": "9P6RFB4DZF8B",
		"platforms": [
			"Kaiju Wars + Legend of Keepers - Monsters & Demons Deluxe Bundle"
		]
	},
	{
		"name": "Kaiju Wars + Legend of Keepers - Monsters & Demons Bundle",
		"price": "$29.99+",
		"image": "https://store-images.s-microsoft.com/image/apps.49145.14153760923638168.70056c2f-5c85-45c9-834c-eedddc61a0de.87ec4f2a-86e3-4330-83c4-2c76cd0f778b?q=90&w=177&h=177",
		"uuid": "9PD93FJZGQ4H",
		"platforms": [
			"Kaiju Wars + Legend of Keepers - Monsters & Demons Bundle"
		]
	},
	{
		"name": "Knowledge Keeper",
		"price": "$4.99",
		"image": "https://store-images.s-microsoft.com/image/apps.59265.14133476171175953.fe000568-5229-4838-a32c-3f0f034bfbb6.e068b4bf-0adc-4d45-ab72-5527f6132047?q=90&w=177&h=177",
		"uuid": "9P9ZDVX3KK4L",
		"platforms": [
			"Knowledge Keeper"
		]
	},
	{
		"name": "Knight's Retreat",
		"price": "$3.99",
		"image": "https://store-images.s-microsoft.com/image/apps.59547.14501145405829278.4068d47c-e6a4-4c69-ad3e-e5a069aa09c6.96bec21e-f3e0-4066-b572-02fcd2319be9?q=90&w=177&h=177",
		"uuid": "9P1SK489FDQF",
		"platforms": [
			"Knight's Retreat"
		]
	},
	{
		"name": "Kinduo",
		"price": "$4.99",
		"image": "https://store-images.s-microsoft.com/image/apps.64768.13551591561616984.75f68627-44e2-4021-ab11-66b9c65e924c.9b188247-eec2-463e-a940-a8b4f5b7aa04?q=90&w=177&h=177",
		"uuid": "9ND3MZJJSZMK",
		"platforms": [
			"Kinduo"
		]
	},
	{
		"name": "Kubics",
		"price": "$4.99",
		"image": "https://store-images.s-microsoft.com/image/apps.22486.13928058350623747.979c4f31-4fb8-47da-a2b4-49f6729a08f1.f22334a0-2747-46fc-93c4-48b93260b66b?q=90&w=177&h=177",
		"uuid": "9N0CJJVN8K7G",
		"platforms": [
			"Kubics"
		]
	},
	{
		"name": "KAMIKO",
		"price": "$4.29",
		"image": "https://store-images.s-microsoft.com/image/apps.63674.14294530786326458.bdc89735-7815-4773-a5fa-ca0beb270808.9740b6d0-da28-46e0-9ac9-91630a2ca969?q=90&w=177&h=177",
		"uuid": "9PMFN912ZTVP",
		"platforms": [
			"KAMIKO"
		]
	},
	{
		"name": "Knightin'+",
		"price": "$5.99",
		"image": "https://store-images.s-microsoft.com/image/apps.6725.13571797186971109.f00ca9ad-18a7-4375-919a-5f3b8bb46f8f.20c443f9-5edb-499a-9b94-52f3637452a4?q=90&w=177&h=177",
		"uuid": "9NC9ZQT24WR4",
		"platforms": [
			"Knightin'+"
		]
	},
	{
		"name": "Knock-Knock",
		"price": "$6.99",
		"image": "https://store-images.s-microsoft.com/image/apps.33806.71079503421004046.d25722dd-0735-46bf-832f-72265a4b0d9e.7815591c-d784-491f-b9f6-f6ba24b8e4b0?q=90&w=177&h=177",
		"uuid": "BVSGDQSL23X5",
		"platforms": [
			"Knock-Knock"
		]
	},
	{
		"name": "Knights and Magic Bundle",
		"price": "$35.99",
		"image": "https://store-images.s-microsoft.com/image/apps.64948.14259887227060632.5b620564-0cab-4860-b55d-928f73afeea6.1bcac401-fb38-481b-a55f-fa05f508b945?q=90&w=177&h=177",
		"uuid": "9PKM57D5493K",
		"platforms": [
			"Knights and Magic Bundle"
		]
	},
	{
		"name": "King Oddball",
		"price": "$4.99+",
		"image": "https://store-images.s-microsoft.com/image/apps.5104.70400067566511065.5c2e6ee0-eabb-4272-8157-a4a315a7618c.d2d22036-c299-4c1d-ace7-ccbdcff1e6ee?q=90&w=177&h=177",
		"uuid": "BTK86T84DFSV",
		"platforms": [
			"King Oddball"
		]
	},
	{
		"name": "Kid Tripp",
		"price": "$3.99",
		"image": "https://store-images.s-microsoft.com/image/apps.6605.13565485003877909.9ed19420-5014-4928-8b8e-ab260674951e.2370b2e5-a086-409a-b6c8-8295d43d4625?q=90&w=177&h=177",
		"uuid": "9NCDXTH8LKN6",
		"platforms": [
			"Kid Tripp"
		]
	},
	{
		"name": "Kick & Fennick",
		"price": "$14.99",
		"image": "https://store-images.s-microsoft.com/image/apps.3803.68272322486108329.60df539f-6c6d-45a1-9943-7a6e4159c030.5e47f5e3-2a6a-4888-a859-2ced4f5cd0a7?q=90&w=177&h=177",
		"uuid": "BQ0TGL55T3N2",
		"platforms": [
			"Kick & Fennick"
		]
	},
	{
		"name": "Kattish",
		"price": "$4.99",
		"image": "https://store-images.s-microsoft.com/image/apps.59957.13727693980302382.b57abda6-8bb5-4ff1-b00e-cd647427c564.8dc1dde0-bd5b-4cd1-b635-998b79766821?q=90&w=177&h=177",
		"uuid": "9NP1DK14F46F",
		"platforms": [
			"Kattish"
		]
	},
	{
		"name": "Know by heart...",
		"price": "$19.99",
		"image": "https://store-images.s-microsoft.com/image/apps.14339.14377771566115180.c839dfaf-8983-433f-bde3-303e08232c30.833e3be2-7573-4be1-9bae-4e86af9a2cd6?q=90&w=177&h=177",
		"uuid": "9NRR3V2VB9MZ",
		"platforms": [
			"Know by heart..."
		]
	},
	{
		"name": "Killer Chambers",
		"price": "$8.99",
		"image": "https://store-images.s-microsoft.com/image/apps.2035.13569539289237578.4e060055-dbd3-4fb3-85ed-7dd4da89b21c.8d4ca4cd-81e3-4205-8057-fa55a35266d5?q=90&w=177&h=177",
		"uuid": "9NC6RG2KRD3C",
		"platforms": [
			"Killer Chambers"
		]
	},
	{
		"name": "KYUB",
		"price": "$9.99",
		"image": "https://store-images.s-microsoft.com/image/apps.50824.69772189340576932.c392ad7b-d243-47be-9b2b-3e9457d4f7a1.dd3c159f-6d73-464b-a892-76c57e407235?q=90&w=177&h=177",
		"uuid": "BRMRVL00XV67",
		"platforms": [
			"KYUB"
		]
	},
	{
		"name": "Kathy Rain",
		"price": "$14.99",
		"image": "https://store-images.s-microsoft.com/image/apps.56354.14087730717392389.9a12fa8c-c13e-4e62-a35e-8a2066fb38b8.d54fd9f2-a028-40f7-8c27-cd00a90d4d11?q=90&w=177&h=177",
		"uuid": "9P8HN2T2SZGB",
		"platforms": [
			"Kathy Rain"
		]
	},
	{
		"name": "Keplerth",
		"price": "$14.99",
		"image": "https://store-images.s-microsoft.com/image/apps.50333.13821329994604169.93645c5e-df5b-4052-8008-c8c8f59491a5.aa6f757c-a973-492b-b09e-c04dd9074f55?q=90&w=177&h=177",
		"uuid": "9MT2FXTBCNDG",
		"platforms": [
			"Keplerth"
		]
	},
	{
		"name": "Kingsway",
		"price": "$9.99",
		"image": "https://store-images.s-microsoft.com/image/apps.43560.14337158422934298.ef10ab8e-a4bf-4155-8d01-9b0a3fe3e689.7ea8fccb-f581-41b3-8ed2-0258caf48a9d?q=90&w=177&h=177",
		"uuid": "9PP2H41H50S5",
		"platforms": [
			"Kingsway"
		]
	},
	{
		"name": "Kingdom Come: Deliverance DLC Collection",
		"price": "$19.99",
		"image": "https://store-images.s-microsoft.com/image/apps.64522.13680779525244739.dd97a83d-831a-4762-a048-f8bac146663f.cd6100e4-7171-47ad-ad88-5d735a7ee024?q=90&w=177&h=177",
		"uuid": "9NJH6SRBL9MQ",
		"platforms": [
			"Kingdom Come: Deliverance DLC Collection"
		]
	},
	{
		"name": "Kuznetsk 1997: Detective Visual Novel",
		"price": "$11.99-20%",
		"image": "https://store-images.s-microsoft.com/image/apps.23605.14280095563874719.f8ea2e32-7d49-4bd0-b56d-b0d86fe1aad1.781cb660-de86-43ee-a00c-702355a5e53a?q=90&w=177&h=177",
		"uuid": "9PJTGTK447L0",
		"platforms": [
			"Kuznetsk 1997: Detective Visual Novel"
		]
	}
]